{"assets":{"B96B30A245631DEC82D7EAD1EB4F07B5":{"type":"texture","index":1,"assetRequest":{"type":"slide","state":"contents","slide":"none"},"url":{"native":"assets\/1567F230-E279-4ADC-A90C-0A9EEDC74B48.pdf"},"width":1920,"height":1080},"BF4DA4CDAA48AF27DA92FFBCF0EE3A5A":{"type":"texture","index":0,"assetRequest":{"type":"slide","state":"contents","slide":"none"},"url":{"native":"assets\/1567F230-E279-4ADC-A90C-0A9EEDC74B48.pdf"},"width":1920,"height":1080}},"events":[{"effects":[{"beginTime":0,"baseLayer":{"animations":[],"initialState":{"affineTransform":[1,0,0,1,0,0],"masksToBounds":false,"rotation":0,"scale":1,"position":{"pointX":960,"pointY":540},"width":1920,"sublayerTransform":[1,0,0,0,0,1,0,0,0,0,1,0,0,0,0,1],"contentsRect":{"y":0,"x":0,"width":1,"height":1},"opacity":1,"edgeAntialiasingMask":251658240,"height":1080,"hidden":false,"anchorPoint":{"pointX":0.5,"pointY":0.5}},"objectID":"0","layers":[{"animations":[],"initialState":{"affineTransform":[1,0,0,1,0,0],"masksToBounds":false,"rotation":0,"scale":1,"position":{"pointX":960,"pointY":540},"width":1920,"sublayerTransform":[1,0,0,0,0,1,0,0,0,0,1,-0.00035007912466775983,0,0,0,1],"contentsRect":{"y":0,"x":0,"width":1,"height":1},"opacity":1,"edgeAntialiasingMask":251658240,"height":1080,"hidden":false,"anchorPoint":{"pointX":0.5,"pointY":0.5}},"layers":[{"animations":[],"layers":[],"texturedRectangle":{"isBackgroundTexture":false,"singleTextureOpacity":1,"textureType":0,"textBaseline":0,"textXHeight":0,"isVerticalText":false},"initialState":{"affineTransform":[1,0,0,1,0,0],"masksToBounds":false,"rotation":0,"scale":1,"position":{"pointX":960,"pointY":540},"width":1920,"sublayerTransform":[1,0,0,0,0,1,0,0,0,0,1,0,0,0,0,1],"contentsRect":{"y":0,"x":0,"width":1,"height":1},"opacity":1,"edgeAntialiasingMask":0,"height":1080,"hidden":false,"anchorPoint":{"pointX":0.5,"pointY":0.5}},"texture":"B96B30A245631DEC82D7EAD1EB4F07B5"},{"animations":[{"timeOffset":0,"from":{"scalar":false},"beginTime":0,"repeatCount":0,"fillMode":"both","property":"hidden","autoreverses":false,"duration":0.01,"to":{"scalar":true}}],"layers":[],"texturedRectangle":{"isBackgroundTexture":false,"singleTextureOpacity":1,"textureType":0,"textBaseline":0,"textXHeight":0,"isVerticalText":false},"initialState":{"affineTransform":[1,0,0,1,0,0],"masksToBounds":false,"rotation":0,"scale":1,"position":{"pointX":960,"pointY":540},"width":1920,"sublayerTransform":[1,0,0,0,0,1,0,0,0,0,1,0,0,0,0,1],"contentsRect":{"y":0,"x":0,"width":1,"height":1},"opacity":1,"edgeAntialiasingMask":0,"height":1080,"hidden":false,"anchorPoint":{"pointX":0.5,"pointY":0.5}},"texture":"BF4DA4CDAA48AF27DA92FFBCF0EE3A5A"}]}]},"effects":[],"duration":0.01,"type":"transition","name":"none","objectID":"0"}],"automaticPlay":false,"hyperlinks":[],"accessibility":[{"text":"async \/ await rules","targetRectangle":{"y":105.75,"x":462.1240234375,"width":995.751953125,"height":114}},{"text":"code can be paused waiting for an Async Function with await","targetRectangle":{"y":287.96875,"x":340.90261140906296,"width":1026.090625,"height":170.40000677108765}},{"text":"await returns whatever the async function returns when it is done.","targetRectangle":{"y":458.36875677108765,"x":340.90261140906296,"width":1239.2406250000001,"height":233.79375800490379}},{"text":"await can only be used inside an async function.","targetRectangle":{"y":692.16251477599144,"x":340.90261140906296,"width":1167.1799999999996,"height":148.59375461935997}},{"text":"exceptions are swallowed by Promise.catch()","targetRectangle":{"y":840.75626939535141,"x":340.90261140906296,"width":1108.68625,"height":148.59375461935997}}],"baseLayer":{"animations":[],"initialState":{"affineTransform":[1,0,0,1,0,0],"masksToBounds":false,"rotation":0,"scale":1,"position":{"pointX":960,"pointY":540},"width":1920,"sublayerTransform":[1,0,0,0,0,1,0,0,0,0,1,0,0,0,0,1],"contentsRect":{"y":0,"x":0,"width":1,"height":1},"opacity":1,"edgeAntialiasingMask":251658240,"height":1080,"hidden":false,"anchorPoint":{"pointX":0.5,"pointY":0.5}},"objectID":"0","layers":[{"animations":[],"initialState":{"affineTransform":[1,0,0,1,0,0],"masksToBounds":false,"rotation":0,"scale":1,"position":{"pointX":960,"pointY":540},"width":1920,"sublayerTransform":[1,0,0,0,0,1,0,0,0,0,1,-0.00035007912466775983,0,0,0,1],"contentsRect":{"y":0,"x":0,"width":1,"height":1},"opacity":1,"edgeAntialiasingMask":251658240,"height":1080,"hidden":false,"anchorPoint":{"pointX":0.5,"pointY":0.5}},"layers":[{"animations":[],"layers":[],"texturedRectangle":{"isBackgroundTexture":false,"singleTextureOpacity":1,"textureType":0,"textBaseline":0,"textXHeight":0,"isVerticalText":false},"initialState":{"affineTransform":[1,0,0,1,0,0],"masksToBounds":false,"rotation":0,"scale":1,"position":{"pointX":960,"pointY":540},"width":1920,"sublayerTransform":[1,0,0,0,0,1,0,0,0,0,1,0,0,0,0,1],"contentsRect":{"y":0,"x":0,"width":1,"height":1},"opacity":1,"edgeAntialiasingMask":0,"height":1080,"hidden":false,"anchorPoint":{"pointX":0.5,"pointY":0.5}},"texture":"BF4DA4CDAA48AF27DA92FFBCF0EE3A5A"}]}]}}]}